mtcnn_onnx_simple/__init__.py
mtcnn_onnx_simple/align.py
mtcnn_onnx_simple/align_transformations.py
mtcnn_onnx_simple/first_stage.py
mtcnn_onnx_simple/helpers.py
mtcnn_onnx_simple/matlab_cpt2form.py
mtcnn_onnx_simple/mtcnn.py
mtcnn_onnx_simple-0.4.dist-info/LICENSE.txt
mtcnn_onnx_simple-0.4.dist-info/METADATA
mtcnn_onnx_simple-0.4.dist-info/WHEEL
mtcnn_onnx_simple-0.4.dist-info/top_level.txt
mtcnn_onnx_simple-0.4.dist-info/RECORD
