Metadata-Version: 2.1
Name: mtcnn_onnx_simple
Version: 0.4
Summary: MTCNN implementation using ONNXRuntime
Author-email: Karthik Sundar <karthiksundar30092002@gmail.com>
Maintainer-email: Karthik Sundar <karthiksundar30092002@gmail.com>
License: Copyright (c) 2012-2024 Scott Chacon and others
Classifier: Programming Language :: Python :: 3
Classifier: License :: OSI Approved :: MIT License
Classifier: Operating System :: OS Independent
License-File: LICENSE.txt
Requires-Dist: numpy >1.18.0
Requires-Dist: opencv-python-headless
Requires-Dist: onnxruntime >=1.4.0
Requires-Dist: pillow >=10.1.0
